is_odd_gpt4oai/__init__.py
is_odd_gpt4oai/main.py
is_odd_gpt4oai-0.0.5.dist-info/LICENSE.txt
is_odd_gpt4oai-0.0.5.dist-info/METADATA
is_odd_gpt4oai-0.0.5.dist-info/WHEEL
is_odd_gpt4oai-0.0.5.dist-info/top_level.txt
is_odd_gpt4oai-0.0.5.dist-info/RECORD
