Metadata-Version: 2.1
Name: is-odd-gpt4oai
Version: 0.0.5
Summary: Check if a number is odd or even
Author: mattekudacy
Author-email: cyrus2952@gmail.com
License-File: LICENSE.txt
Requires-Dist: openai
